Metadata-Version: 2.1
Name: econometricc-test
Version: 0.0
Summary: Econometrics tests and models
Author-email: dmitriyalmazof1@gmail.com
